json_file_helper/__init__.py
json_file_helper/json_file.py
json_file_helper-0.1.2.dist-info/LICENSE
json_file_helper-0.1.2.dist-info/METADATA
json_file_helper-0.1.2.dist-info/WHEEL
json_file_helper-0.1.2.dist-info/RECORD
