Metadata-Version: 2.3
Name: json_file_helper
Version: 0.1.2
Summary: Classes for easier file usage, currently only json is implemented.
License: MIT
Author: TheBiemGamer
Author-email: 47662596+TheBiemGamer@users.noreply.github.com
Requires-Python: >=3.8
Classifier: License :: OSI Approved :: MIT License
Classifier: Programming Language :: Python :: 3
Classifier: Programming Language :: Python :: 3.8
Classifier: Programming Language :: Python :: 3.9
Classifier: Programming Language :: Python :: 3.10
Classifier: Programming Language :: Python :: 3.11
Classifier: Programming Language :: Python :: 3.12
Classifier: Programming Language :: Python :: 3.13
Requires-Dist: jsonschema (>=4.23.0,<5.0.0)
Project-URL: Source Code, https://github.com/TheBiemGamer/json-file-helper
